colorcodetools/__init__.py
colorcodetools/cmyk/__init__.py
colorcodetools/cmyk/config.py
colorcodetools/cmyk/convert.py
colorcodetools/cmyk/invert.py
colorcodetools/cmyk/validate.py
colorcodetools/hex/__init__.py
colorcodetools/hex/config.py
colorcodetools/hex/convert.py
colorcodetools/hex/invert.py
colorcodetools/hex/validate.py
colorcodetools/ral/__init__.py
colorcodetools/ral/config.py
colorcodetools/ral/validate.py
colorcodetools/rgb/__init__.py
colorcodetools/rgb/config.py
colorcodetools/rgb/convert.py
colorcodetools/rgb/invert.py
colorcodetools/rgb/validate.py
colorcodetools-0.3.0.dist-info/LICENSE
colorcodetools-0.3.0.dist-info/METADATA
colorcodetools-0.3.0.dist-info/WHEEL
colorcodetools-0.3.0.dist-info/top_level.txt
colorcodetools-0.3.0.dist-info/RECORD
