Metadata-Version: 2.1
Name: colorcodetools
Version: 0.3.0
Summary: Some powerful color tools
Home-page: https://github.com/TheKeineAhnung/colorcodes
Author: Keine Ahnung
Author-email: kontakt@keineahnung.eu
License: LICENSE
Project-URL: Bug Tracker, https://github.com/TheKeineAhnung/colorcodes/issues
Platform: UNKNOWN
Classifier: Programming Language :: Python :: 3.6
Classifier: License :: OSI Approved :: MIT License
Classifier: Operating System :: OS Independent
Requires-Python: >=3.6
